<PAMDataset>
  <Metadata>
    <MDI key="DataType">Thematic</MDI>
  </Metadata>
  <PAMRasterBand band="1">
    <Histograms>
      <HistItem>
        <HistMin>-0.5</HistMin>
        <HistMax>31.5</HistMax>
        <BucketCount>32</BucketCount>
        <IncludeOutOfRange>1</IncludeOutOfRange>
        <Approximate>0</Approximate>
        <HistCounts>4152|3569|43|23671|2375|65095|2166|1781|1391|1440|1343|477|414|125|58|3010|97|1449|232|1694|1614|2182|1544|240|99965|2410|85801|391|57|539|761|183</HistCounts>
      </HistItem>
    </Histograms>
    <Metadata>
      <MDI key="RepresentationType">THEMATIC</MDI>
      <MDI key="STATISTICS_COVARIANCES">95.32940341604852</MDI>
      <MDI key="STATISTICS_EXCLUDEDVALUES"></MDI>
      <MDI key="STATISTICS_MAXIMUM">31</MDI>
      <MDI key="STATISTICS_MEAN">17.58824117137</MDI>
      <MDI key="STATISTICS_MINIMUM">0</MDI>
      <MDI key="STATISTICS_SKIPFACTORX">1</MDI>
      <MDI key="STATISTICS_SKIPFACTORY">1</MDI>
      <MDI key="STATISTICS_STDDEV">9.7636777607646</MDI>
    </Metadata>
  </PAMRasterBand>
</PAMDataset>
